[
        //Warrior Class
        {
		"name": "Warrior Bug",
		"unitType": "Sword",
		"replaces": "Warrior",
		"uniqueTo": "Insectoids",
    		"cost": 50,
		"movement": 3,
		"strength": 9,
		"obsoleteTech": "Metal Casting",
                "upgradesTo": "Tough Warrior",
    		"uniques": 
		[
			"Can only be built <in this city> <if [Warrior Broods] is constructed> <hidden from users>",
			"Cannot be purchased <hidden from users>",
			"Heals [12] damage if it kills a unit <hidden from users>",
			"Gain [5] [Science] (modified by game speed) <upon being defeated> <hidden from users>",
			"Gain [5] [Science] (modified by game speed) <upon being promoted> <hidden from users>",
			"Gain [2] [Science] (modified by game speed) <upon ending a turn in a [All] tile> <hidden from users>",
			"Gain [2] [Science] (modified by game speed) <when attacking> <hidden from users>",
			"Gain [2] [Science] (modified by game speed) <when defending> <hidden from users>"
		],
  	},
        {
		"name": "Tough Warrior",
		"unitType": "Sword",
		"replaces": "Spearman",
		"uniqueTo": "Insectoids",
		"movement": 2,
		"strength": 13,
		"cost": 100,
		"requiredTech": "Bronze Working",
		"obsoleteTech": "Civil Service",
                "upgradesTo": "Armored Warrior",
		"uniques": 
		[
			"Can only be built <in this city> <if [Warrior Broods] is constructed> <hidden from users>",
			"[+50]% Strength <vs [Mounted] units>",
			"Cannot be purchased <hidden from users>",
			"Heals [5] damage if it kills a unit <hidden from users>",
			"Gain [5] [Science] (modified by game speed) <upon being defeated> <hidden from users>",
			"Gain [5] [Science] (modified by game speed) <upon being promoted> <hidden from users>",
			"Gain [2] [Science] (modified by game speed) <upon ending a turn in a [All] tile> <hidden from users>",
			"Gain [2] [Science] (modified by game speed) <when attacking> <hidden from users>",
			"Gain [2] [Science] (modified by game speed) <when defending> <hidden from users>"
		],
		"attackSound": "metalhit"
	},
        {
		"name": "Armored Warrior",
		"unitType": "Sword",
		"replaces": "Musketman",
		"uniqueTo": "Insectoids",
		"movement": 2,
		"strength": 26,
		"cost": 300,
		"requiredTech": "Gunpowder",
		"obsoleteTech": "Rifling",
                "upgradesTo": "Tough Armor Warrior",
		"uniques": 
		[
			"Only available <in this city> <in cities with at least [20] [Population]> <hidden from users>",
			"Heals [9] damage if it kills a unit <hidden from users>",
			"Gain [10] [Science] (modified by game speed) <upon being defeated> <hidden from users>",
			"Gain [10] [Science] (modified by game speed) <upon being promoted> <hidden from users>",
			"Gain [5] [Science] (modified by game speed) <upon ending a turn in a [All] tile> <hidden from users>",
			"Gain [5] [Science] (modified by game speed) <when attacking> <hidden from users>",
			"Gain [5] [Science] (modified by game speed) <when defending> <hidden from users>",
		],
		"attackSound": "metalhit"
	},
        {
		"name": "Tough Armor Warrior",
		"unitType": "Gunpowder",
                "replaces": "Great War Infantry",
		"uniqueTo": "Insectoids",
		"movement": 1,
		"strength": 55,
		"cost": 400,
		"requiredTech": "Replaceable Parts",
		"obsoleteTech": "Plastics",
		"upgradesTo": "Large Warrior",
		"uniques": 
		[
			"Only available <in this city> <in cities with at least [20] [Population]> <hidden from users>",
			"Heals [9] damage if it kills a unit <hidden from users>",
			"Gain [10] [Science] (modified by game speed) <upon being defeated> <hidden from users>",
			"Gain [10] [Science] (modified by game speed) <upon being promoted> <hidden from users>",
			"Gain [5] [Science] (modified by game speed) <upon ending a turn in a [All] tile> <hidden from users>",
			"Gain [5] [Science] (modified by game speed) <when attacking> <hidden from users>",
			"Gain [5] [Science] (modified by game speed) <when defending> <hidden from users>",
		],
		"attackSound": "metalhit"
	},
	{
		"name": "Large Warrior",
		"unitType": "Gunpowder",
		"replaces": "Infantry",
		"uniqueTo": "Insectoids",
		"movement": 2,
		"strength": 73,
		"cost": 900,
		"requiredTech": "Plastics",
		"obsoleteTech": "Mobile Tactics",
		"uniques": 
		[
			"Only available <in this city> <in cities with at least [20] [Population]> <hidden from users>",
			"Heals [9] damage if it kills a unit <hidden from users>",
			"Gain [10] [Science] (modified by game speed) <upon being defeated> <hidden from users>",
			"Gain [10] [Science] (modified by game speed) <upon being promoted> <hidden from users>",
			"Gain [5] [Science] (modified by game speed) <upon ending a turn in a [All] tile> <hidden from users>",
			"Gain [5] [Science] (modified by game speed) <when attacking> <hidden from users>",
			"Gain [5] [Science] (modified by game speed) <when defending> <hidden from users>",
		],
		"attackSound": "metalhit"
	},
        //Charger Class
        {
		"name": "Mutated Warrior Bug",
		"unitType": "Mounted",
		"replaces": "Horseman",
		"uniqueTo": "Insectoids",
		"movement": 4,
		"strength": 8,
		"cost": 100,
		"requiredTech": "Horseback Riding",
		"requiredResource": "Horses",
		"obsoleteTech": "Chivalry",
                "upgradesTo": "Light Charger",
		"uniques": 
		[
			"Can only be built <in this city> <if [Warrior Broods] is constructed> <hidden from users>",
			"Cannot be purchased <hidden from users>",
			"Can move after attacking",
			"No defensive terrain bonus",
			"[-30]% Strength <vs cities> <when attacking>",
			"Heals [2] damage if it kills a unit <hidden from users>",
			"Gain [8] [Science] (modified by game speed) <upon being defeated> <hidden from users>",
			"Gain [8] [Science] (modified by game speed) <upon being promoted> <hidden from users>",
			"Gain [4] [Science] (modified by game speed) <upon ending a turn in a [All] tile> <hidden from users>",
			"Gain [4] [Science] (modified by game speed) <when attacking> <hidden from users>",
			"Gain [4] [Science] (modified by game speed) <when defending> <hidden from users>"
		],
		"hurryCostModifier": 20,
		"attackSound": "horse"
	},
        {
		"name": "Light Charger",
		"unitType": "Siege",
		"replaces": "Catapult",
		"uniqueTo": "Insectoids",
		"movement": 2,
		"strength": 15,
		"cost": 150,
		"requiredTech": "Mathematics",
		"obsoleteTech": "Physics",
                "upgradesTo": "Charger",
		"uniques": 
		[
			"Can only be built <in this city> <if [Warrior Broods] is constructed> <hidden from users>",
			"Cannot be purchased <hidden from users>",
			"[+20]% Strength <vs cities> <when attacking>", 
			"No defensive terrain bonus",
			"Must set up to ranged attack", 
			"[-1] Sight",
			"Heals [5] damage if it kills a unit <hidden from users>",
			"Gain [5] [Science] (modified by game speed) <upon being defeated> <hidden from users>",
			"Gain [5] [Science] (modified by game speed) <upon being promoted> <hidden from users>",
			"Gain [1] [Science] (modified by game speed) <upon ending a turn in a [All] tile> <hidden from users>",
			"Gain [1] [Science] (modified by game speed) <when attacking> <hidden from users>",
			"Gain [1] [Science] (modified by game speed) <when defending> <hidden from users>"
		],
		"hurryCostModifier": 20,
		"attackSound": "throw"
	},
        {
		"name": "Crusher",
		"unitType": "Mounted",
		"replaces": "Knight",
		"uniqueTo": "Insectoids",
		"movement": 4,
		"strength": 24,
		"cost": 250,
		"requiredTech": "Chivalry",
		"obsoleteTech": "Military Science",
		"requiredResource": "Horses",
                "upgradesTo": "Armored Crusher",
		"uniques": 
		[
			"Can only be built <in this city> <if [Warrior Broods] is constructed> <hidden from users>",
			"Can move after attacking",
			"No defensive terrain bonus",
			"[-30]% Strength <vs cities> <when attacking>",
			"Cannot be purchased <hidden from users>",
			"Only available <in this city> <in cities with at least [10] [Population]> <hidden from users>",
			"Heals [5] damage if it kills a unit <hidden from users>",
			"Gain [5] [Science] (modified by game speed) <upon being defeated> <hidden from users>",
			"Gain [5] [Science] (modified by game speed) <upon being promoted> <hidden from users>",
			"Gain [1] [Science] (modified by game speed) <upon ending a turn in a [All] tile> <hidden from users>",
			"Gain [1] [Science] (modified by game speed) <when attacking> <hidden from users>",
			"Gain [1] [Science] (modified by game speed) <when defending> <hidden from users>"
		],
		"attackSound": "horse"
	},
        {
		"name": "Charger",
		"unitType": "Siege",
		"replaces": "Trebuchet",
		"uniqueTo": "Insectoids",
		"movement": 1,
		"strength": 25,
		"cost": 300,
		"requiredTech": "Physics",
		"obsoleteTech": "Electronics",
		"uniques": 
		[
			"[+40]% Strength <vs cities> <when attacking>",
			"No defensive terrain bonus",
			"[-1] Sight",
			"Only available <in this city> <in cities with at least [15] [Population]> <hidden from users>",
			"Heals [5] damage if it kills a unit <hidden from users>",
			"Gain [10] [Science] (modified by game speed) <upon being defeated> <hidden from users>",
			"Gain [10] [Science] (modified by game speed) <upon being promoted> <hidden from users>",
			"Gain [1] [Science] (modified by game speed) <upon ending a turn in a [All] tile> <hidden from users>",
			"Gain [1] [Science] (modified by game speed) <when attacking> <hidden from users>",
			"Gain [1] [Science] (modified by game speed) <when defending> <hidden from users>"
		],
		"attackSound": "throw"
	},
        {
		"name": "Armored Crusher",
		"unitType": "Siege",
		"replaces": "Cannon",
		"uniqueTo": "Insectoids",
		"movement": 1,
		"strength": 18,
		"cost": 400,
		"requiredTech": "Chemistry",
		"obsoleteTech": "Dynamite",
		"upgradesto": "Heavy Crusher",
		"uniques": 
		[
			"Only available <in this city> <in cities with at least [30] [Population]> <hidden from users>",
			"[+80]% Strength <vs cities> <when attacking>",
			"No defensive terrain bonus",
			"[-1] Sight <hidden from users>",
			"[+30]% Strength <vs [Mounted] units> <hidden from users>",
			"Cannot be purchased <hidden from users>",
			"Heals [5] damage if it kills a unit <hidden from users>",
			"Gain [10] [Science] (modified by game speed) <upon being defeated> <hidden from users>",
			"Gain [10] [Science] (modified by game speed) <upon being promoted> <hidden from users>",
			"Gain [1] [Science] (modified by game speed) <upon ending a turn in a [All] tile> <hidden from users>",
			"Gain [1] [Science] (modified by game speed) <when attacking> <hidden from users>",
			"Gain [1] [Science] (modified by game speed) <when defending> <hidden from users>"
		],
		"attackSound": "metalhit"
	},
	 {
		"name": "Heavy Crusher",
		"unitType": "Siege",
		"uniqueTo": "Insectoids",
		"movement": 2,
		"strength": 50,
		"cost": 900,
		"requiredTech": "Combined Arms",
		"obsoleteTech": "Computers",
		"uniques": 
		[
			"[+30]% Strength <vs [Armored] units>",
			"Only available <in this city> <in cities with at least [30] [Population]> <hidden from users>",
			"[+100]% Strength <vs cities> <when attacking>",
			"No defensive terrain bonus",
			"[-1] Sight <hidden from users>",
			"Cannot be purchased <hidden from users>",
			"Heals [5] damage if it kills a unit <hidden from users>",
			"Gain [10] [Science] (modified by game speed) <upon being defeated> <hidden from users>",
			"Gain [10] [Science] (modified by game speed) <upon being promoted> <hidden from users>",
			"Gain [1] [Science] (modified by game speed) <upon ending a turn in a [All] tile> <hidden from users>",
			"Gain [1] [Science] (modified by game speed) <when attacking> <hidden from users>",
			"Gain [1] [Science] (modified by game speed) <when defending> <hidden from users>"
		],
		"attackSound": "metalhit"
	},

        //Spewer Class
        {
		"name": "Spewer Bug",
		"unitType": "Archery",
		"replaces": "Archer",
		"uniqueTo": "Insectoids",
		"obsoleteTech": "Construction",
    		"cost": 50,
		"rangedStrength": 8,
		"movement": 3,
		"strength": 6,
                "upgradesTo": "Acid Spewer",
    		"uniques": 
		[			
			"Can only be built <in this city> <if [Warrior Broods] is constructed> <hidden from users>",
			"Cannot be purchased <hidden from users>",
			"Founds a new city <by consuming this unit> <hidden from users>", 
			"Requires at least [2] population <hidden from users>",
			"Heals [5] damage if it kills a unit <hidden from users>",
			"Gain [10] [Science] (modified by game speed) <upon being defeated> <hidden from users>",
			"Gain [10] [Science] (modified by game speed) <upon being promoted> <hidden from users>",
			"Gain [1] [Science] (modified by game speed) <upon ending a turn in a [All] tile> <hidden from users>",
			"Gain [1] [Science] (modified by game speed) <when attacking> <hidden from users>",
			"Gain [1] [Science] (modified by game speed) <when defending> <hidden from users>"
		],
  	},
        {
		"name": "Acid Spewer",
		"unitType": "Archery",
		"replaces": "Chariot Archer",
		"uniqueTo": "Insectoids",
		"obsoleteTech": "Chivalry",
    		"cost": 100,
		"movement": 3,
		"strength": 8,
		"requiredTech": "The Wheel",
                "upgradesTo": "Bile Spewer",
    		"uniques": 
		[	
			"Can only be built <in this city> <if [Pools of Acid] is constructed> <hidden from users>",
			"Cannot be purchased <hidden from users>",
			"Heals [8] damage if it kills a unit <hidden from users>",
			"Gain [10] [Science] (modified by game speed) <upon being defeated> <hidden from users>",
			"Gain [10] [Science] (modified by game speed) <upon being promoted> <hidden from users>",
			"Gain [1] [Science] (modified by game speed) <upon ending a turn in a [All] tile> <hidden from users>",
			"Gain [1] [Science] (modified by game speed) <when attacking> <hidden from users>",
			"Gain [1] [Science] (modified by game speed) <when defending> <hidden from users>"
		],
  	},
        {
		"name": "Bile Spewer",
		"unitType": "Archery",
		"replaces": "Composite Bowman",
		"uniqueTo": "Insectoids",
		"movement": 1,
		"strength": 11,
		"rangedStrength": 16,
		"cost": 200,
		"requiredTech": "Construction",
		"obsoleteTech": "Machinery",
		"upgradesTo": "Armored Acid Spewer",
		"uniques": 
		[
			"Can only be built <in this city> <if [Warrior Broods] is constructed> <hidden from users>",
                        "Can only be built <in this city> <if [Pools of Acid] is constructed> <hidden from users>",
			"Cannot be purchased <hidden from users>",
			"Only available <in this city> <in cities with at least [9] [Population]> <hidden from users>",
			"Heals [5] damage if it kills a unit <hidden from users>",
			"Gain [10] [Science] (modified by game speed) <upon being defeated> <hidden from users>",
			"Gain [10] [Science] (modified by game speed) <upon being promoted> <hidden from users>",
			"Gain [5] [Science] (modified by game speed) <upon ending a turn in a [All] tile> <hidden from users>",
			"Gain [5] [Science] (modified by game speed) <when attacking> <hidden from users>",
			"Gain [5] [Science] (modified by game speed) <when defending> <hidden from users>"
		],
		"upgradesTo": "Crossbowman",
		"attackSound": "arrow"
	},
        {
		"name": "Armored Acid Spewer",
		"unitType": "Ranged Gunpowder",
		"replaces": "Gatling Gun",
		"uniqueTo": "Insectoids",
		"range": 1,
		"movement": 2,
		"strength": 32,
		"rangedStrength": 32,
		"cost": 300,
		"uniques": 
		[
			"Only available <in this city> <in cities with at least [30] [Population]> <hidden from users>",
                        "Can only be built <in this city> <if [Corrosive Acids Production Pods] is constructed> <hidden from users>",
			"[+50]% Strength <vs cities> <when attacking>",
			"[-1] Sight <hidden from users>",
			"[-20]% Strength <vs [Mounted] units> <hidden from users>",
			"Cannot be purchased <hidden from users>",
			"Heals [5] damage if it kills a unit <hidden from users>",
			"Gain [10] [Science] (modified by game speed) <upon being defeated> <hidden from users>",
			"Gain [10] [Science] (modified by game speed) <upon being promoted> <hidden from users>",
			"Gain [5] [Science] (modified by game speed) <upon ending a turn in a [All] tile> <hidden from users>",
			"Gain [5] [Science] (modified by game speed) <when attacking> <hidden from users>",
			"Gain [5] [Science] (modified by game speed) <when defending> <hidden from users>"
		],
		"requiredTech": "Industrialization",
		"obsoleteTech": "Ballistics",
		"attackSound": "machinegun"
	},
        
        //Stalker Class
        {
		"name": "Scout Stalker",
		"unitType": "Scout",
		"replaces": "Scout",
		"uniqueTo": "Insectoids",
		"obsoleteTech": "Scientific Theory",
    		"cost": 50,
		"movement": 3,
		"strength": 6,
                "upgradesTo": "Stalkers",
    		"uniques": 
		[
			"Cannot be purchased <hidden from users>",
			"Can build [Land] improvements on tiles <hidden from users>", 
			"Heals [8] damage if it kills a unit <hidden from users>",
			"Gain [10] [Science] (modified by game speed) <upon being defeated> <hidden from users>",
			"Gain [20] [Science] (modified by game speed) <upon being promoted> <hidden from users>",
			"Gain [5] [Science] (modified by game speed) <upon ending a turn in a [All] tile> <hidden from users>",
			"Gain [5] [Science] (modified by game speed) <when attacking> <hidden from users>",
			"Gain [5] [Science] (modified by game speed) <when defending> <hidden from users>"
		],
  	},
        {
		"name": "Stalkers",
		"unitType": "Archery",
		"replaces": "Crossbowman",
		"uniqueTo": "Insectoids",
		"movement": 4,
		"strength": 25,
		"cost": 400,
		"requiredTech": "Machinery",
		"obsoleteTech": "Computers",
		"uniques": 
		[
			"Can only be built <in this city> <if [Warrior Broods] is constructed> <hidden from users>",
			"Can only be built <in this city> <if [Camouflage Mutation Pods] is constructed> <hidden from users>",
			"Can move after attacking <hidden from users>",
			"Invisible to non-adjacent units <hidden from users>",
			"Can see invisible [Wounded] units <hidden from users>",
			"[-50]% Strength <vs cities> <when attacking>",
			"Cannot be purchased <hidden from users>",
			"Only available <in this city> <in cities with at least [30] [Population]> <hidden from users>",
			"Heals [5] damage if it kills a unit <hidden from users>",
			"Gain [10] [Science] (modified by game speed) <upon being defeated> <hidden from users>",
			"Gain [10] [Science] (modified by game speed) <upon being promoted> <hidden from users>",
			"Gain [5] [Science] (modified by game speed) <upon ending a turn in a [All] tile> <hidden from users>",
			"Gain [5] [Science] (modified by game speed) <when attacking> <hidden from users>",
			"Gain [5] [Science] (modified by game speed) <when defending> <hidden from users>",
			"[+50]% Strength <during the [Classical era]> <hidden from users>",
			"[+100]% Strength <during the [Medieval era]> <hidden from users>",
			"[+150]% Strength <during the [Renaissance era]> <hidden from users>",
			"[+250]% Strength <during the [Industrial era]> <hidden from users>",
			"[+1] Movement <starting from the [Industrial era]> <hidden from users>",
			"[+350]% Strength <during the [Modern era]> <hidden from users>",
			"[+400]% Strength <during the [Atomic era]> <hidden from users>",
			"[+450]% Strength <during the [Information era]> <hidden from users>",
			"[+500]% Strength <during the [Future era]> <hidden from users>"
		],
		"attackSound": "metalhit"
	},
        {
		"name": "Scavengers",
		"replaces": "Cavalry",
		"uniqueTo": "Insectoids",
		"unitType": "Sword",
		"movement": 2,
		"strength": 36,
		"cost": 200,
		"requiredTech": "Military Science",
		"obsoleteTech": "Combustion",
                "upgradesTo": "Stalker Scavenger",
		"uniques": 
		[
			"Can move after attacking",
			"No defensive terrain bonus",
			"Only available <in this city> <in cities with at least [20] [Population]> <hidden from users>",
			"Can only be built <in this city> <if [Camouflage Mutation Pods] is constructed> <hidden from users>",
			"Cannot be purchased <hidden from users>",
			"Heals [5] damage if it kills a unit <hidden from users>",
			"Gain [10] [Science] (modified by game speed) <upon being defeated> <hidden from users>",
			"Gain [10] [Science] (modified by game speed) <upon being promoted> <hidden from users>",
			"Gain [1] [Science] (modified by game speed) <upon ending a turn in a [All] tile> <hidden from users>",
			"Gain [1] [Science] (modified by game speed) <when attacking> <hidden from users>",
			"Gain [1] [Science] (modified by game speed) <when defending> <hidden from users>"
		],
		"attackSound": "metalhit"
	},
        {
		"name": "Stalker Scavenger",
		"replaces": "Rifleman",
		"uniqueTo": "Insectoids",
		"unitType": "Sword",
		"movement": 3,
		"strength": 44,
		"cost": 500,
		"uniques": 
		[
			"Unbuildable",
			"Can move after attacking",
			"No defensive terrain bonus",
			"[-50]% Strength <vs cities> <when attacking>", 
			"Only available <in this city> <in cities with at least [30] [Population]> <hidden from users>",
			"Cannot be purchased <hidden from users>",
			"Heals [5] damage if it kills a unit <hidden from users>",
			"Gain [5] [Science] (modified by game speed) <upon being defeated> <hidden from users>",
			"Gain [5] [Science] (modified by game speed) <upon being promoted> <hidden from users>",
			"Gain [5] [Science] (modified by game speed) <upon ending a turn in a [All] tile> <hidden from users>",
			"Gain [2] [Science] (modified by game speed) <when attacking> <hidden from users>",
			"Gain [2] [Science] (modified by game speed) <when defending> <hidden from users>"
		],
		"requiredTech": "Rifling",
		"obsoleteTech": "Replaceable Parts",
		"attackSound": "metalhit"
	},
        //Water Type Class
        {
		"name": "Water Walkers",
		"unitType": "Melee Water",
		"replaces": "Trireme",
		"uniqueTo": "Insectoids",
		"obsoleteTech": "Astronomy",
    		"cost": 100,
		"movement": 3,
		"strength": 8,
		"requiredTech": "Sailing",
                "upgradesTo": "Hardened Water Walkers",
    		"uniques": 
		[	
			"Can only be built <in this city> <if [Water Eggs Incubation Chamber] is constructed> <hidden from users>",
			"Cannot enter ocean tiles", 
			"Cannot be purchased <hidden from users>",
			"Heals [12] damage if it kills a unit <hidden from users>",
			"Gain [10] [Science] (modified by game speed) <upon being defeated> <hidden from users>",
			"Gain [20] [Science] (modified by game speed) <upon being promoted> <hidden from users>",
			"Gain [5] [Science] (modified by game speed) <upon ending a turn in a [All] tile> <hidden from users>",
			"Gain [5] [Science] (modified by game speed) <when attacking> <hidden from users>",
			"Gain [5] [Science] (modified by game speed) <when defending> <hidden from users>"
		],
  	},
        {
		"name": "Hardened Water Walkers",
		"unitType": "Ranged Water",
		"replaces": "Galleass",
		"uniqueTo": "Insectoids",
		"movement": 3,
		"strength": 19,
		"cost": 200,
		"requiredTech": "Compass",
                "upgradesTo": "Armored Water Walker",
		"obsoleteTech": "Navigation",
		"uniques": 
		[
			"Can only be built <in this city> <if [Water Eggs Incubation Chamber] is constructed> <hidden from users>",
			"Cannot enter ocean tiles",
			"Cannot be purchased <hidden from users>",
			"Only available <in this city> <in cities with at least [4] [Population]> <hidden from users>",
			"Heals [5] damage if it kills a unit <hidden from users>",
			"Gain [10] [Science] (modified by game speed) <upon being defeated> <hidden from users>",
			"Gain [10] [Science] (modified by game speed) <upon being promoted> <hidden from users>",
			"Gain [5] [Science] (modified by game speed) <upon ending a turn in a [All] tile> <hidden from users>",
			"Gain [5] [Science] (modified by game speed) <when attacking> <hidden from users>",
			"Gain [5] [Science] (modified by game speed) <when defending> <hidden from users>"
		],
		"attackSound": "arrow"
	},
        {
		"name": "Agile Water Walkers",
		"unitType": "Melee Water",
		"replaces": "Caravel",
		"uniqueTo": "Insectoids",
		"movement": 4,
		"strength": 23,
		"cost": 200,
		"requiredTech": "Astronomy",
		"obsoleteTech": "Combustion",
		"uniques": 
		[
			"Cannot be purchased <hidden from users>",
			"Can only be built <in this city> <if [Water Eggs Incubation Chamber] is constructed> <hidden from users>",
			"[+1] Sight", 
                        "Only available <in this city> <in cities with at least [10] [Population]> <hidden from users>",
			"Heals [9] damage if it kills a unit <hidden from users>",
			"Gain [5] [Science] (modified by game speed) <upon being defeated> <hidden from users>",
			"Gain [5] [Science] (modified by game speed) <upon being promoted> <hidden from users>",
			"Gain [1] [Science] (modified by game speed) <upon ending a turn in a [All] tile> <hidden from users>",
			"Gain [1] [Science] (modified by game speed) <when attacking> <hidden from users>",
			"Gain [1] [Science] (modified by game speed) <when defending> <hidden from users>",
			"May withdraw before melee ([50]%)"
		],
		"hurryCostModifier": 30,
		"attackSound": "metalhit"
	},
        {
		"name": "Mirage Walkers",
		"unitType": "Melee Water",
		"replaces": "Privateer",
		"uniqueTo": "Insectoids",
		"movement": 6,
		"strength": 30,
		"cost": 400,
		"requiredTech": "Navigation",
		"promotions": 
		[
			"Coastal Raider I"
		],
		"uniques": 
		[
			"Cannot be purchased <hidden from users>",
                        "Only available <in this city> <in cities with at least [15] [Population]> <hidden from users>",
			"Can only be built <in this city> <if [Water Eggs Incubation Chamber] is constructed> <hidden from users>",
			"May capture killed [Water] units",
			"Heals [9] damage if it kills a unit <hidden from users>",
			"Gain [10] [Science] (modified by game speed) <upon being defeated> <hidden from users>",
			"Gain [10] [Science] (modified by game speed) <upon being promoted> <hidden from users>",
			"Gain [1] [Science] (modified by game speed) <upon ending a turn in a [All] tile> <hidden from users>",
			"Gain [1] [Science] (modified by game speed) <when attacking> <hidden from users>",
			"Gain [1] [Science] (modified by game speed) <when defending> <hidden from users>",
		],
		"attackSound": "metalhit"
	},
        {
		"name": "Water-Adapted Diving Warrior",
		"unitType": "Melee Water",
		"replaces": "Frigate",
		"uniqueTo": "Insectoids",
		"movement": 4,
		"strength": 30,
		"cost": 250,
		"requiredTech": "Navigation",
		"obsoleteTech": "Electronics",
		"uniques": 
		[
			"Cannot be purchased <hidden from users>",
                        "Can only be built <in this city> <if [Warrior Broods] is constructed> <hidden from users>",
			"Can only be built <in this city> <if [Water Eggs Incubation Chamber] is constructed> <hidden from users>",
                        "Only available <in this city> <in cities with at least [25] [Population]> <hidden from users>",
			"May capture killed [Water] units",
			"Heals [9] damage if it kills a unit <hidden from users>",
			"Gain [10] [Science] (modified by game speed) <upon being defeated> <hidden from users>",
			"Gain [10] [Science] (modified by game speed) <upon being promoted> <hidden from users>",
			"Gain [1] [Science] (modified by game speed) <upon ending a turn in a [All] tile> <hidden from users>",
			"Gain [1] [Science] (modified by game speed) <when attacking> <hidden from users>",
			"Gain [1] [Science] (modified by game speed) <when defending> <hidden from users>",
		],
		"hurryCostModifier": 20,
		"attackSound": "metalhit"
	},
        {
		"name": "Armored Water Walker",
		"unitType": "Melee Water",
                "replaces": "Ironclad",
		"uniqueTo": "Insectoids",
		"movement": 2,
		"strength": 50,
		"cost": 500,
		"requiredTech": "Steam Power",
		"obsoleteTech": "Combustion",
		"uniques": 
                [
			"Cannot be purchased <hidden from users>",
			"Consumes [1] [Biomass]",
                        "Can only be built <in this city> <if [Water Eggs Incubation Chamber] is constructed> <hidden from users>",
                        "[+33]% Strength <vs cities>",
                        "Only available <in this city> <in cities with at least [25] [Population]> <hidden from users>",
                        "Double movement in [Coast]", 
                        "Heals [9] damage if it kills a unit <hidden from users>",
			"Gain [10] [Science] (modified by game speed) <upon being defeated> <hidden from users>",
			"Gain [10] [Science] (modified by game speed) <upon being promoted> <hidden from users>",
			"Gain [3] [Science] (modified by game speed) <upon ending a turn in a [All] tile> <hidden from users>",
			"Gain [1] [Science] (modified by game speed) <when attacking> <hidden from users>",
			"Gain [1] [Science] (modified by game speed) <when defending> <hidden from users>",
                ],
		"attackSound": "shipguns"
	},
        {
		"name": "Aquatic Arachnid",
		"unitType": "Submarine",
                "replaces": "Submarine",
		"uniqueTo": "Insectoids",
		"movement": 2,
		"strength": 55,
		"cost": 270,
		"requiredTech": "Refrigeration",
		"uniqueTo": "Insectoids",
		"movement": 3,
		"strength": 68,
		"cost": 500,
		"requiredResource": "Biomass",
		"requiredTech": "Electronics",
		"uniques": 
		[
			"Cannot be purchased <hidden from users>",
			"Can only be built <in this city> <if [Water Eggs Incubation Chamber] is constructed> <hidden from users>",
			"Can only be built <in this city> <if [Metal-Infused Egg Broods] is constructed> <hidden from users>",
                        "Only available <in this city> <in cities with at least [45] [Population]> <hidden from users>",
			"Never appears as a Barbarian unit"
		],
		"promotions": 
		[
			"Indirect Fire"
		],
		"attackSound": "shipguns"
	},
	
        //Titan Class
        {
		"name": "Bile Titan",
		"unitType": "Sword",
		"replaces": "Lancer",
		"uniqueTo": "Insectoids",
		"movement": 1,
		"strength": 40,
		"cost": 500,
		"requiredTech": "Metallurgy",
		"obsoleteTech": "Combined Arms",
		"upgradesTo": "Armored Bile Titan",
		"uniques": 
		[
			"Cannot be purchased <hidden from users>",
			"[-1] population [in this city]",
                        "Consumes [1] [Biomass]",
			"Can move after attacking",
			"No defensive terrain bonus",
			"May capture killed [Water] units",
			"[+40]% Strength <vs cities> <when attacking>",
			"Can only be built <in this city> <if [Larger Brood Chambers] is constructed> <hidden from users>",
			"Heals [5] damage if it kills a unit <hidden from users>",
			"Gain [20] [Science] (modified by game speed) <upon being defeated> <hidden from users>",
			"Gain [20] [Science] (modified by game speed) <upon being promoted> <hidden from users>",
			"Gain [10] [Science] (modified by game speed) <upon ending a turn in a [All] tile> <hidden from users>",
			"Gain [10] [Science] (modified by game speed) <when attacking> <hidden from users>",
			"Gain [10] [Science] (modified by game speed) <when defending> <hidden from users>",
			"[+50]% Strength <during the [Classical era]> <hidden from users>",
			"[+100]% Strength <during the [Medieval era]> <hidden from users>",
			"[+150]% Strength <during the [Renaissance era]> <hidden from users>",
			"[+250]% Strength <during the [Industrial era]> <hidden from users>",
			"[+1] Movement <starting from the [Modern era]> <hidden from users>",
			"[+400]% Strength <during the [Modern era]> <hidden from users>",
		],
		"attackSound": "metalhit"
	},
	 {
		"name": "Armored Bile Titan",
		"unitType": "Sword",
		"replaces": "Tank",
		"uniqueTo": "Insectoids",
		"movement": 1,
		"strength": 80,
		"cost": 1000,
		"requiredTech": "Combined Arms",
		"uniques": 
		[
			"Cannot be purchased <hidden from users>",
			"[-1] population [in this city]",
                        "Consumes [2] [Biomass]",
			"Can move after attacking",
			"No defensive terrain bonus",
			"May capture killed [Water] units",
			"[+50]% Strength <vs cities> <when attacking>",
			"Can only be built <in this city> <if [Larger Brood Chambers] is constructed> <hidden from users>",
			"Heals [5] damage if it kills a unit <hidden from users>",
			"Gain [20] [Science] (modified by game speed) <upon being defeated> <hidden from users>",
			"Gain [20] [Science] (modified by game speed) <upon being promoted> <hidden from users>",
			"Gain [10] [Science] (modified by game speed) <upon ending a turn in a [All] tile> <hidden from users>",
			"Gain [10] [Science] (modified by game speed) <when attacking> <hidden from users>",
			"Gain [10] [Science] (modified by game speed) <when defending> <hidden from users>",
			"[+50]% Strength <during the [Atomic era]> <hidden from users>",
			"[+100]% Strength <during the [Information era]> <hidden from users>",
			"[+150]% Strength <during the [Future era]> <hidden from users>",
		],
		"attackSound": "metalhit"
	},

        //Centipede Class
        {
		"name": "Burrowing Crawler",
                "replaces": "Artillery",
		"uniqueTo": "Insectoids",
		"unitType": "Siege",
		"movement": 2,
		"strength": 30,
		"cost": 400,
		"requiredTech": "Dynamite",
		"uniques": 
                [
			"Cannot be purchased <hidden from users>",
                        "[+100]% Strength <vs cities> <when attacking>",
                        "[-2] Sight", 
                        "Can only be built <in this city> <if [Crawler Brood Chambers] is constructed> <hidden from users>",
                        "Only available <in this city> <in cities with at least [25] [Population]> <hidden from users>",
                        "Heals [9] damage if it kills a unit <hidden from users>",
			"Gain [10] [Science] (modified by game speed) <upon being defeated> <hidden from users>",
			"Gain [10] [Science] (modified by game speed) <upon being promoted> <hidden from users>",
			"Gain [1] [Science] (modified by game speed) <upon ending a turn in a [All] tile> <hidden from users>",
			"Gain [1] [Science] (modified by game speed) <when attacking> <hidden from users>",
			"Gain [1] [Science] (modified by game speed) <when defending> <hidden from users>",
                ],
		"promotions": 
                [
                        "Indirect Fire"
                ],
		"attackSound": "metalhit"
	},
	{
		"name": "Tough Crawler",
		"unitType": "Sword",
		"replaces": "Machine Gun",
		"uniqueTo": "Insectoids",
		"movement": 2,
		"strength": 70,
		"cost": 700,
		"requiredTech": "Ballistics",
		"uniques": 
                [
			"Cannot be purchased <hidden from users>",
                        "[+200]% Strength <vs cities> <when attacking>",
                        "[-2] Sight", 
                        "Can only be built <in this city> <if [Crawler Brood Chambers] is constructed> <hidden from users>",
                        "Only available <in this city> <in cities with at least [45] [Population]> <hidden from users>",
                        "Heals [14] damage if it kills a unit <hidden from users>",
			"Gain [10] [Science] (modified by game speed) <upon being defeated> <hidden from users>",
			"Gain [10] [Science] (modified by game speed) <upon being promoted> <hidden from users>",
			"Gain [1] [Science] (modified by game speed) <upon ending a turn in a [All] tile> <hidden from users>",
			"Gain [1] [Science] (modified by game speed) <when attacking> <hidden from users>",
			"Gain [1] [Science] (modified by game speed) <when defending> <hidden from users>",
                ],
		"attackSound": "metalhit"
	},

        //Aerial Class
        {
		"name": "Winged Mutate Warrior",
		"unitType": "Fighter",
                "replaces": "Triplane",
		"uniqueTo": "Insectoids",
		"movement": 1,
		"strength": 25,
		"rangedStrength": 25,
		"range": 4,
		"interceptRange": 3,
		"cost":  420,
		"requiredTech": "Flight",
		"obsoleteTech": "Radar",
		"uniques": 
                [
			"Cannot be purchased <hidden from users>",
                        "[20]% chance to intercept air attacks", 
                        "[+30]% Strength <vs [Bomber] units>", 
                        "[+30]% Strength <vs [Helicopter] units>",
                        "Can only be built <in this city> <if [Mutation Inbcubators] is constructed> <hidden from users>",
                        "Only available <in this city> <in cities with at least [30] [Population]> <hidden from users>",
                        "Heals [9] damage if it kills a unit <hidden from users>",
			"Gain [20] [Science] (modified by game speed) <upon being defeated> <hidden from users>",
			"Gain [20] [Science] (modified by game speed) <upon being promoted> <hidden from users>",
			"Gain [10] [Science] (modified by game speed) <upon ending a turn in a [All] tile> <hidden from users>",
			"Gain [10] [Science] (modified by game speed) <when attacking> <hidden from users>",
			"Gain [10] [Science] (modified by game speed) <when defending> <hidden from users>",
                ],
		"attackSound": "metalhit"
	},
	{
		"name": "Gliderlings",
		"unitType": "Sword",
                "replaces": "Paratrooper",
		"uniqueTo": "Insectoids",
		"movement": 2,
		"strength": 40,
		"cost": 450,
		"requiredTech": "Radar",
		"uniques": 
                [
			"Cannot be purchased <hidden from users>",
			"May Paradrop up to [5] tiles from inside friendly territory",
			"Never appears as a Barbarian unit <hidden from users>",
                        "Can only be built <in this city> <if [Mutation Inbcubators] is constructed> <hidden from users>",
                        "Only available <in this city> <in cities with at least [10] [Population]> <hidden from users>",
                        "Heals [9] damage if it kills a unit <hidden from users>",
			"Gain [10] [Science] (modified by game speed) <upon being defeated> <hidden from users>",
			"Gain [10] [Science] (modified by game speed) <upon being promoted> <hidden from users>",
			"Gain [1] [Science] (modified by game speed) <upon ending a turn in a [All] tile> <hidden from users>",
			"Gain [1] [Science] (modified by game speed) <when attacking> <hidden from users>",
			"Gain [1] [Science] (modified by game speed) <when defending> <hidden from users>",
                ],
		"attackSound": "metalhit"
	},
        {
		"name": "Winged Mutate Stalker",
		"unitType": "Bomber",
		"uniqueTo": "Insectoids",
		"replaces": "Great War Bomber",
		"movement": 1,
		"strength": 30,
		"rangedStrength": 30,
		"range": 4,
		"cost": 450,
		"requiredTech": "Flight",
		"obsoleteTech": "Radar",
                "uniques": 
                [
			"Cannot be purchased <hidden from users>",
                        "Can only be built <in this city> <if [Mutation Inbcubators] is constructed> <hidden from users>",
                        "Only available <in this city> <in cities with at least [30] [Population]> <hidden from users>",
                        "Heals [9] damage if it kills a unit <hidden from users>",
			"Gain [20] [Science] (modified by game speed) <upon being defeated> <hidden from users>",
			"Gain [20] [Science] (modified by game speed) <upon being promoted> <hidden from users>",
			"Gain [10] [Science] (modified by game speed) <upon ending a turn in a [All] tile> <hidden from users>",
			"Gain [10] [Science] (modified by game speed) <when attacking> <hidden from users>",
			"Gain [10] [Science] (modified by game speed) <when defending> <hidden from users>",
                ],
		"attackSound": "metalhit"
	},

        //Worker Class
	{
		"name": "Lesser Worker Bug",
		"unitType": "Civilian",
		"replaces": "Worker",
		"uniqueTo": "Insectoids",
    		"cost": 60,
		"movement": 3,
    		"uniques": 
		[
			"Can only be built <in this city> <if [Nesting] is constructed> <hidden from users>",
			"Can build [Land] improvements on tiles", 
			"Automation is a primary action",
			"Heals [10] damage if it kills a unit <hidden from users>",
			"Cannot be purchased <hidden from users>",
			"Requires at least [3] population <hidden from users>",
			"Gain [5] [Science] (modified by game speed) <upon being defeated> <hidden from users>",
			"Gain [10] [Science] (modified by game speed) <upon being promoted> <hidden from users>",
			"Gain [2] [Science] (modified by game speed) <upon ending a turn in a [All] tile> <hidden from users>",
			"Gain [2] [Science] (modified by game speed) <when attacking> <hidden from users>",
			"Gain [2] [Science] (modified by game speed) <when defending> <hidden from users>"
		],
  	},
        {
		"name": "Worker Bug",
		"unitType": "Sword",
		"uniqueTo": "Insectoids",
    		"cost": 120,
		"movement": 2,
		"strength": 5,
    		"uniques": 
		[
			"Can only be built <in this city> <if [Nesting] is constructed> <hidden from users>",
			"Can build [Land] improvements on tiles", 
			"Automation is a primary action",
			"Heals [10] damage if it kills a unit <hidden from users>",
			"Cannot be purchased <hidden from users>",
			"Founds a new city <by consuming this unit> <hidden from users>", 
			"Requires at least [3] population <hidden from users>",
			"Gain [10] [Science] (modified by game speed) <upon being defeated> <hidden from users>",
			"Gain [20] [Science] (modified by game speed) <upon being promoted> <hidden from users>",
			"Gain [5] [Science] (modified by game speed) <upon ending a turn in a [All] tile> <hidden from users>",
			"Gain [5] [Science] (modified by game speed) <when attacking> <hidden from users>",
			"Gain [5] [Science] (modified by game speed) <when defending> <hidden from users>"
		],
  	},
        {
		"name": "Insectoid Divers",
		"unitType": "Melee Water",
		"replaces": "Work Boats",
		"uniqueTo": "Insectoids",
    		"cost": 70,
		"movement": 4,
		"strength": 10,
		"requiredTech": "Sailing",
    		"uniques": 
		[			
			"Can only be built <in this city> <if [Water Eggs Incubation Chamber] is constructed> <hidden from users>",
			"Cannot be purchased <hidden from users>",
			"Heals [10] damage if it kills a unit <hidden from users>",
			"Gain [10] [Science] (modified by game speed) <upon being defeated> <hidden from users>",
			"Gain [10] [Science] (modified by game speed) <upon being promoted> <hidden from users>",
			"Gain [5] [Science] (modified by game speed) <upon ending a turn in a [All] tile> <hidden from users>",
			"Gain [5] [Science] (modified by game speed) <when attacking> <hidden from users>",
			"Gain [5] [Science] (modified by game speed) <when defending> <hidden from users>",
			"Cannot enter ocean tiles <before discovering [Astronomy]>", 
			"May create improvements on water resources",
            		"Automation is a primary action"
		],
  	},
        //Special Class
        {
		"name": "Hive Queen",
		"unitType": "Sword",
		"replaces": "Settler",
		"uniqueTo": "Insectoids",
    		"cost": 500,
		"movement": 2,
		"strength": 20,
    		"uniques": 
		[			
			"Cannot be purchased <hidden from users>",
			"[-20]% Strength <for [All] units> <for [10] turns> <upon being defeated>",
			"Founds a new city <by consuming this unit> <hidden from users>", 
			"Requires at least [10] population <hidden from users>",
			"Heals [30] damage if it kills a unit <hidden from users>",
			"[+50]% Strength <during the [Classical era]> <hidden from users>",
			"[+100]% Strength <during the [Medieval era]> <hidden from users>",
			"[+150]% Strength <during the [Renaissance era]> <hidden from users>",
			"[+200]% Strength <during the [Industrial era]> <hidden from users>",
			"[+1] Movement <starting from the [Industrial era]> <hidden from users>",
			"[+250]% Strength <during the [Modern era]> <hidden from users>",
			"[+300]% Strength <during the [Atomic era]> <hidden from users>",
			"[+350]% Strength <during the [Information era]> <hidden from users>",
			"[+400]% Strength <during the [Future era]> <hidden from users>",
			"[+1] Movement <starting from the [Information era]> <hidden from users>",
			"Gain [10] [Science] (modified by game speed) <upon being defeated> <hidden from users>",
			"Gain [40] [Science] (modified by game speed) <upon being promoted> <hidden from users>",
			"Gain [20] [Science] (modified by game speed) <upon ending a turn in a [All] tile> <hidden from users>",
			"Gain [10] [Science] (modified by game speed) <when attacking> <hidden from users>",
			"Gain [10] [Science] (modified by game speed) <when defending> <hidden from users>",
			"Never appears as a Barbarian unit <hidden from users>"
		],
  	},

	//Structured Units
	
	{
		"name": "Experimental Hive Carrier",
		"unitType": "Aircraft Carrier",
		"replaces": "Carrier",
		"uniqueTo": "Insectoids",
		"movement": 3,
		"strength": 35,
		"cost": 345,
		"requiredTech": "Computers",
		"obsoleteTech": "Telecommunications",
		"upgradesTo": "Structured Hive Carrier",
		"uniques": 
		[
			"Cannot be purchased <hidden from users>",
			"Can only be built <in this city> <if [Structured Seaport] is constructed> <hidden from users>",
                        "Only available <in this city> <in cities with at least [40] [Population]> <hidden from users>",
			"Never appears as a Barbarian unit <hidden from users>",
			"Cannot attack", 
			"Consumes [2] [Oil]",
			"Can carry [2] [Aircraft] units"
		]
	},
	{
		"name": "Structured Hive Carrier",
		"unitType": "Aircraft Carrier",
		"uniqueTo": "Insectoids",
		"movement": 4,
		"strength": 45,
		"cost": 555,
		"requiredTech": "Telecommunications",
		"obsoleteTech": "Globalization",
		"upgradesTo": "Heavy Hive Carrier",
		"uniques": 
		[
			"Cannot be purchased <hidden from users>",
			"Can only be built <in this city> <if [Structured Seaport] is constructed> <hidden from users>",
                        "Only available <in this city> <in cities with at least [40] [Population]> <hidden from users>",
			"Never appears as a Barbarian unit <hidden from users>",
			"Cannot attack", 
			"Consumes [1] [Oil]",
			"Can carry [4] [Aircraft] units"
		]
	},
	{
		"name": "Heavy Hive Carrier",
		"unitType": "Aircraft Carrier",
		"replaces": "Swordsman",
		"uniqueTo": "Insectoids",
		"movement": 5,
		"strength": 55,
		"cost": 1500,
		"requiredTech": "Globalization",
		"uniques": 
		[
			"Cannot be purchased <hidden from users>",
			"Can only be built <in this city> <if [Structured Seaport] is constructed> <hidden from users>",
                        "Only available <in this city> <in cities with at least [40] [Population]> <hidden from users>",
			"Never appears as a Barbarian unit <hidden from users>",
			"Cannot attack", 
			"Consumes [1] [High-Tech Composite]",
			"Can carry [6] [Aircraft] units"
		]
	},
	{
		"name": "Droneship Carrier",
		"unitType": "Aircraft Carrier",
		"replaces": "Battleship",
		"uniqueTo": "Insectoids",
		"movement": 4,
		"strength": 70,
		"cost": 2500,
		"requiredTech": "Globalization",
		"uniques": 
		[
			"Cannot be purchased <hidden from users>",
			"Can only be built <in this city> <if [Structured Seaport] is constructed> <hidden from users>",
                        "Only available <in this city> <in cities with at least [60] [Population]> <hidden from users>",
			"Never appears as a Barbarian unit <hidden from users>",
			"Consumes [2] [High-Tech Composite]",
			"Consumes [1] [Uranium]",
			"Consumes [1] [Robotic Parts]",
			"Consumes [1] [Oil]",
			"Can carry [10] [Aircraft] units"
		]
	},
	{
		"name": "Drone Rocket Artillery",
		"unitType": "Siege",
		"replaces": "Rocket Artillery",
		"uniqueTo": "Insectoids",
		"movement": 2,
		"strength": 45,
		"rangedStrength": 60,
		"range": 3,
		"cost": 900,
		"requiredTech": "Robotics",
		"requiredResource": "Aluminum",
		"uniques": 
		[
			"Cannot be purchased <hidden from users>",
			"Can only be built <in this city> <if [Robotic Drones Production Facility] is constructed> <hidden from users>",
                        "Only available <in this city> <in cities with at least [80] [Population]> <hidden from users>",
			"[+200]% Strength <vs cities> <when attacking>",
			"No defensive terrain bonus",
			"[-1] Sight", 
			"Never appears as a Barbarian unit"
		],
		"promotions": 
		[
			"Indirect Fire",
			"Ground Drone",
		],
		"attackSound": "artillery"
	},
	{
		"name": "Mobile Drone SAM",
		"unitType": "Gunpowder",
		"replaces": "Mobile SAM",
		"uniqueTo": "Insectoids",
		"movement": 3,
		"interceptRange": 2,
		"strength": 65,
		"cost": 900,
		"requiredTech": "Rocketry",
		"uniques": 
		[
			"Cannot be purchased <hidden from users>",
			"Can only be built <in this city> <if [Robotic Drones Production Facility] is constructed> <hidden from users>",
                        "Only available <in this city> <in cities with at least [80] [Population]> <hidden from users>",
			"[100]% chance to intercept air attacks", 
			"[+150]% Strength <vs [Air] units>",
			"[+150]% Strength <vs [Helicopter] units>", 
			"Never appears as a Barbarian unit"
		],
		"promotions": 
		[
			"Ground Drone",
		],
		"attackSound": "missile"
	},
	{
		"name": "Hovering Gunship Drone",
		"unitType": "Helicopter",
		"replaces": "Helicopter Gunship",
		"uniqueTo": "Insectoids",
		"movement": 6,
		"strength": 60,
		"cost": 900,
		"requiredTech": "Robotics",
		"requiredResource": "Aluminum",
		"uniques": 
		[
			"Cannot be purchased <hidden from users>",
			"Can only be built <in this city> <if [Robotic Drones Production Facility] is constructed> <hidden from users>",
			"Can only be built <in this city> <if [Droneport] is constructed> <hidden from users>",
                        "Only available <in this city> <in cities with at least [40] [Population]> <hidden from users>",
			"[+80]% Strength <vs [Armored] units> <hidden from users>", 
			"No defensive terrain bonus <hidden from users>", 
			"Can move after attacking <hidden from users>",
			"All tiles cost 1 movement <hidden from users>", 
			"Ignores Zone of Control <hidden from users>", 
			"Unable to capture cities", 
			"Never appears as a Barbarian unit <hidden from users>"
		],
		"promotions": 
		[
			"Air Support Drone",
		],
		"attackSound": "machinegun"
	},
	{
		"name": "Nuclear Drone Submarine",
		"unitType": "Submarine",
		"replaces": "Nuclear Submarine",
		"uniqueTo": "Insectoids",
		"movement": 6,
		"strength": 50,
		"range": 3,
		"rangedStrength": 85,
		"cost": 900,
		"requiredTech": "Telecommunications",
		"uniques": 
		[
			"Cannot be purchased <hidden from users>",
			"Can only be built <in this city> <if [Robotic Drones Production Facility] is constructed> <hidden from users>",
                        "Only available <in this city> <in cities with at least [80] [Population]> <hidden from users>",
			"[+75]% Strength <when attacking>", 
			"Can only attack [Water] tiles", 
			"[+1] Sight", 
			"Can carry [2] [Missile] units", 
			"Never appears as a Barbarian unit"
		],
		"promotions": 
		[
			"Naval Drone",
		],
		"attackSound": "torpedo"
	},
	{
		"name": "Drone Infantry Unit",
		"unitType": "Gunpowder",
		"replaces": "Mechanized Infantry",
		"uniqueTo": "Insectoids",
		"movement": 2,
		"strength": 70,
		"cost": 1300,
		"requiredTech": "Mobile Tactics",
		"uniques": 
		[
			"Cannot be purchased <hidden from users>",
			"Can only be built <in this city> <if [Robotic Drones Production Facility] is constructed> <hidden from users>",
                        "Only available <in this city> <in cities with at least [40] [Population]> <hidden from users>",
			"Never appears as a Barbarian unit"
		],
		"promotions": 
		[
			"Ground Drone",
		],
		"attackSound": "tankshot"
	},
	{
		"name": "Amphibious Drone Unit",
		"unitType": "Gunpowder",
		"replaces": "Marine",
		"uniqueTo": "Insectoids",
		"movement": 2,
		"strength": 65,
		"cost": 1100,
		"requiredTech": "Mobile Tactics",
		"uniques": 
		[
			"Cannot be purchased <hidden from users>",
			"Can only be built <in this city> <if [Robotic Drones Production Facility] is constructed> <hidden from users>",
                        "Only available <in this city> <in cities with at least [40] [Population]> <hidden from users>",
			"Never appears as a Barbarian unit"
		],
		"promotions": 
		[
			"Ground Drone",
		],
		"attackSound": "tankshot"
	},
	{
		"name": "Missile Cruiser Drone",
		"unitType": "Ranged Water",
		"replaces": "Missile Cruiser",
		"uniqueTo": "Insectoids",
		"movement": 5,
		"strength": 70,
		"rangedStrength": 80,
		"range": 2,
		"interceptRange": 2,
		"cost": 1500,
		"requiredTech": "Robotics",
		"uniques": 
		[
			"Cannot be purchased <hidden from users>",
			"Can only be built <in this city> <if [Structured Seaport] is constructed> <hidden from users>",
			"Can only be built <in this city> <if [Robotic Drones Production Facility] is constructed> <hidden from users>",
                        "Only available <in this city> <in cities with at least [40] [Population]> <hidden from users>",
			"[100]% chance to intercept air attacks", 
			"Can see invisible [Submarine] units",
			"Can carry [3] [Missile] units", 
			"[+100]% Strength <vs [Submarine] units>", 
			"Never appears as a Barbarian unit"
		],
		"promotions": 
		[
			"Indirect Fire",
			"Ground Drone",
		],
		"attackSound": "shipguns"
	},
	{
		"name": "Armored Drone Vehicles",
		"unitType": "Armored",
		"replaces": "Modern Armor",
		"uniqueTo": "Insectoids",
		"movement": 5,
		"strength": 90,
		"cost": 1200,
		"requiredTech": "Lasers",
		"requiredResource": "Aluminum",
		"uniques": 
		[
			"Cannot be purchased <hidden from users>",
			"Can only be built <in this city> <if [Robotic Drones Production Facility] is constructed> <hidden from users>",
                        "Only available <in this city> <in cities with at least [40] [Population]> <hidden from users>",
			"Can move after attacking", 
			"No defensive terrain bonus", 
			"Never appears as a Barbarian unit"
		],
		"promotions": 
		[
			"Ground Drone",
		],
		"attackSound": "tankshot"
	},
	{
		"name": "Drone Jet Fighter",
		"unitType": "Fighter",
		"replaces": "Jet Fighter",
		"uniqueTo": "Insectoids",
		"movement": 1,
		"strength": 75,
		"rangedStrength": 75,
		"range": 12,
		"interceptRange": 10,
		"cost": 2000,
		"requiredTech": "Lasers",
		"requiredResource": "Aluminum",
		"upgradesTo": "Fighter Jet Stealth Drone",
		"uniques": 
		[
			"Cannot be purchased <hidden from users>",
			"Can only be built <in this city> <if [Robotic Drones Production Facility] is constructed> <hidden from users>",
			"Can only be built <in this city> <if [Droneport] is constructed> <hidden from users>",
                        "Only available <in this city> <in cities with at least [40] [Population]> <hidden from users>",
			"[100]% chance to intercept air attacks", 
			"[+150]% Strength <vs [Bomber] units>", 
			"[+150]% Strength <vs [Helicopter] units>"
		],
		"promotions": 
		[
			"Aerial Drone",
		],
		"attackSound": "jetgun"
	},
	{
		"name": "Titan Drone",
		"unitType": "Armored",
		"replaces": "Giant Death Robot",
		"uniqueTo": "Insectoids",
		"movement": 4,
		"strength": 120,
		"cost": 3000,
		"requiredTech": "Nuclear Fusion",
		"requiredResource": "Uranium",
		"upgradesTo": "Super Titan Drone",
		"uniques": 
		[
			"Cannot be purchased <hidden from users>",
			"Can only be built <in this city> <if [Robotic Drones Production Facility] is constructed> <hidden from users>",
                        "Only available <in this city> <in cities with at least [50] [Population]> <hidden from users>",
			"Can move after attacking", 
			"No defensive terrain bonus", 
			"Never appears as a Barbarian unit"
		],
		"promotions": 
		[
			"Ground Drone",
		],
		"attackSound": "gdrAttack"
	},
	{
		"name": "Super Titan Drone",
		"unitType": "Armored",
		"replaces": "Destroyer",
		"uniqueTo": "Insectoids",
		"movement": 3,
		"strength": 170,
		"cost": 5000,
		"requiredTech": "Nuclear Fusion",
		"uniques": 
		[
			"Cannot be purchased <hidden from users>",
			"Consumes [1] [Uranium]",
			"Consumes [1] [High-Tech Composite]",
			"Consumes [1] [Robotic Parts]",
			"Unbuildable",
			"Can move after attacking", 
			"No defensive terrain bonus"
		],
		"promotions": 
		[
			"Ground Drone",
		],
		"attackSound": "gdrAttack"
	},
	{
		"name": "Fighter Jet Stealth Drone",
		"unitType": "Fighter",
		"uniqueTo": "Insectoids",
		"replaces": "Fighter",
		"movement": 2,
		"strength": 110,
		"rangedStrength": 110,
		"range": 20,
		"cost": 2500,
		"requiredTech": "Globalization",
		"uniques": 
		[
			"Cannot be purchased <hidden from users>",
			"Consumes [1] [Aluminum]",
			"Consumes [1] [High-Tech Composite]",
			"Unbuildable",
			"Damage taken from interception reduced by [80]%", 
			"[+4] Sight", 
			"Can see over obstacles"
		],
		"promotions": 
		[
			"Aerial Drone",
		],
		"attackSound": "bombing"
	},
	{
		"name": "Bomber Drone",
		"unitType": "Bomber",
		"uniqueTo": "Insectoids",
		"replaces": "Bomber",
		"movement": 2,
		"strength": 75,
		"rangedStrength": 75,
		"range": 22,
		"cost": 1500,
		"requiredTech": "Globalization",
		"upgradesTo": "Stealth Bomber Drone",
		"requiredResource": "Aluminum",
		"uniques": 
		[
			"Cannot be purchased <hidden from users>",
			"Can only be built <in this city> <if [Droneport] is constructed> <hidden from users>",
			"Can only be built <in this city> <if [Robotic Drones Production Facility] is constructed> <hidden from users>",
			"Only available <in this city> <in cities with at least [50] [Population]> <hidden from users>",
			"Damage taken from interception reduced by [50]%", 
			"[+2] Sight", 
			"Can see over obstacles"
		],
		"promotions": 
		[
			"Aerial Drone",
		],
		"attackSound": "bombing"
	},
	{
		"name": "Stealth Bomber Drone",
		"unitType": "Bomber",
		"uniqueTo": "Insectoids",
		"replaces": "Stealth Bomber",
		"movement": 2,
		"strength": 150,
		"rangedStrength": 150,
		"range": 28,
		"cost": 2500,
		"requiredTech": "Stealth",
		"upgradesTo": "Atom Bomber Drone",
		"uniques": 
		[
			"Cannot be purchased <hidden from users>",
			"Unbuildable",
			"Damage taken from interception reduced by [90]% <hidden from users>", 
			"[+4] Sight <hidden from users>", 
			"Can see over obstacles <hidden from users>",
			"Consumes [1] [Uranium]",
			"Consumes [1] [High-Tech Composite]",
			"Consumes [1] [Robotic Parts]",
		],
		"promotions": 
		[
			"Aerial Drone",
		],
			
		"attackSound": "bombing"
	},
	{
		"name": "Atom Bomber Drone",
		"unitType": "Bomber",
		"uniqueTo": "Insectoids",
		"replaces": "Anti-Tank Gun",
		"movement": 2,
		"strength": 150,
		"rangedStrength": 150,
		"range": 20,
		"cost": 4000,
		"requiredTech": "Stealth",
		"upgradesTo": "Nuclear Stealth Bomber Drone",
		"uniques": 
		[
			"Cannot be purchased <hidden from users>",
			"Unbuildable",
			"Can only be built <in this city> <if [Droneport] is constructed> <hidden from users>",
			"Can only be built <in this city> <if [Robotic Drones Production Facility] is constructed> <hidden from users>",
			"Only available <in this city> <in cities with at least [70] [Population]> <hidden from users>",
			"Nuclear weapon of Strength [1] <hidden from users>", 
			"Blast radius [0] <hidden from users>",
			"Consumes [1] [Uranium]",
			"Consumes [1] [High-Tech Composite]",
			"Consumes [1] [Robotic Parts]",
		],
		"promotions": 
		[
			"Aerial Drone",
		],
			
		"attackSound": "bombing"
	},
	{
		"name": "Nuclear Stealth Bomber Drone",
		"unitType": "Bomber",
		"uniqueTo": "Insectoids",
		"replaces": "Pikeman",
		"movement": 3,
		"strength": 200,
		"rangedStrength": 200,
		"range": 30,
		"cost": 10000,
		"requiredTech": "Stealth",
		"uniques": 
		[
			"Cannot be purchased <hidden from users>",
			"Unbuildable",
			"Can only be built <in this city> <if [Droneport] is constructed> <hidden from users>",
			"Can only be built <in this city> <if [Robotic Drones Production Facility] is constructed> <hidden from users>",
			"Only available <in this city> <in cities with at least [100] [Population]> <hidden from users>",
			"Nuclear weapon of Strength [2] <hidden from users>", 
			"Blast radius [1] <hidden from users>",
			"Consumes [2] [Uranium]",
			"Consumes [2] [High-Tech Composite]",
			"Consumes [1] [Robotic Parts]",
		],
		"promotions": 
		[
			"Aerial Drone",
		],
			
		"attackSound": "bombing"
	},

	//Bombs and Missiles

	{
		"name": "Experimental Atomic Bomb",
		"unitType": "Atomic Bomber",
		"replaces": "Atomic Bomb",
		"uniqueTo": "Insectoids",
		"movement": 1,
		"strength": 75,
		"rangedStrength": 75,
		"range": 10,
		"cost": 400,
		"requiredTech": "Atomic Theory",
		"obsoleteTech": "Nuclear Fission",
		"requiredResource": "Uranium",
		"upgradesTo": "Structured Atomic Bomb",
		"uniques": 
		[
			"Cannot be purchased <hidden from users>",
			"Can only be built <in this city> <if [Learn Structured Planning] is constructed> <hidden from users>",
			"Nuclear weapon of Strength [1]", 
			"Only available <if [Manhattan Project] is constructed>", 
			"Self-destructs when attacking",
			"Blast radius [1]"
		],
		"attackSound": "nuke"

	},
	{
		"name": "Structured Atomic Bomb",
		"unitType": "Atomic Bomber",
		"uniqueTo": "Insectoids",
		"movement": 1,
		"strength": 150,
		"rangedStrength": 150,
		"range": 10,
		"cost": 800,
		"requiredTech": "Nuclear Fission",
		"requiredResource": "Uranium",
		"promotions" : ["Evasion"],
		"uniques": 
		[
			"Cannot be purchased <hidden from users>",
			"Can only be built <in this city> <if [Learn Structured Planning] is constructed> <hidden from users>",
			"Nuclear weapon of Strength [1]", 
			"Only available <if [Manhattan Project] is constructed>", 
			"Self-destructs when attacking",
			"Blast radius [2]"
		],
		"attackSound": "nuke"
	},
	{
		"name": "Expiremental Guided Missile",
		"unitType": "Missile",
		"replaces": "Guided Missile",
		"uniqueTo": "Insectoids",
		"movement": 1,
		"strength": 30,
		"rangedStrength": 30,
		"range": 4,
		"cost": 350,
		"requiredTech": "Rocketry",
		"obsoleteTech": "Advanced Ballistics",
		"uniques": 
		[
			"Cannot be purchased <hidden from users>",
			"Can only be built <in this city> <if [Learn Structured Planning] is constructed> <hidden from users>",
			"[-100]% maintenance costs"
		],
		"attackSound": "missile"
	},
	{
		"name": "Structured Guided Missile",
		"unitType": "Missile",
		"uniqueTo": "Insectoids",
		"replaces": "Landship",
		"movement": 1,
		"strength": 60,
		"rangedStrength": 60,
		"range": 8,
		"cost": 700,
		"requiredTech": "Advanced Ballistics",
		"uniques": 
		[
			"Cannot be purchased <hidden from users>",
			"Can only be built <in this city> <if [Missile Production Facility] is constructed> <hidden from users>",
			"[-100]% maintenance costs"
		],
		"attackSound": "missile"
	},
	{
		"name": "Hypersonic Missile",
		"unitType": "Missile",
		"uniqueTo": "Insectoids",
		"replaces": "Anti-Aircraft Gun",
		"movement": 1,
		"strength": 90,
		"rangedStrength": 90,
		"range": 14,
		"cost": 1000,
		"requiredTech": "Particle Physics",
		"uniques": 
		[
			"Cannot be purchased <hidden from users>",
			"Can only be built <in this city> <if [Missile Production Facility] is constructed> <hidden from users>",
			"[-100]% maintenance costs"
		],
		"attackSound": "missile"
	},
	{
		"name": "Structured Nuclear Missile",
		"unitType": "Missile",
		"replaces": "Nuclear Missile",
		"uniqueTo": "Insectoids",
		"movement": 1,
		"strength": 300,
		"rangedStrength": 300,
		"range": 12,
		"cost": 2500,
		"requiredTech": "Advanced Ballistics",
		"upgradesTo": "Antimatter Missile",
		"uniques": 
		[
			"Cannot be purchased <hidden from users>",
			"Can only be built <in this city> <if [Missile Production Facility] is constructed> <hidden from users>",
			"Nuclear weapon of Strength [2]", 
			"Only available <if [Manhattan Project] is constructed>",
			"Blast radius [2]", 
			"Consumes [2] [Uranium]"
		],
		"attackSound": "nuke"
	},
	{
		"name": "Antimatter Missile",
		"unitType": "Missile",
		"replaces": "Longswordsman",
		"uniqueTo": "Insectoids",
		"movement": 1,
		"strength": 600,
		"rangedStrength": 600,
		"range": 20,
		"cost": 5500,
		"requiredTech": "Particle Physics",
		"uniques": 
		[
			"Cannot be purchased <hidden from users>",
			"Can only be built <in this city> <if [Missile Production Facility] is constructed> <hidden from users>",
			"Nuclear weapon of Strength [3]", 
			"Only available <if [Manhattan Project] is constructed>",
			"Blast radius [4]", 
			"Consumes [3] [Uranium]",
			"Consumes [1] [High-Tech Composite]",
		],
		"attackSound": "nuke"
	},

	//Great Units

	{
		"name": "Landmark Builder",
		"unitType": "Civilian",
		"replaces": "Great Artist",
		"uniqueTo": "Insectoids",
		"uniques": 
		[
            		"Empire enters a [8]-turn Golden Age <by consuming this unit>",
            		"Can instantly construct a [Ancestral Statues] improvement <by consuming this unit>",
            		"Great Insectoid - [Culture]", 
			"Unbuildable", 
			"Uncapturable"
		],
		"movement": 2
	},
	{
		"name": "Testing Site Builder",
		"unitType": "Civilian",
		"replaces": "Great Scientist",
		"uniqueTo": "Insectoids",
		"uniques": 
		[
           		"Can hurry technology research",
            		"Can instantly construct a [Testing Site] improvement <by consuming this unit>",
            		"Great Insectoid - [Science]", 
			"Unbuildable", 
			"Uncapturable"
		],
		"movement": 2
	},
	{
		"name": "Minting Site Builder",
		"unitType": "Civilian",
		"replaces": "Great Merchant",
		"uniqueTo": "Insectoids",
		"uniques": 
		[
            		"Can instantly construct a [Minting Grounds] improvement <by consuming this unit>",
			"Great Insectoid - [Gold]", 
			"Unbuildable", 
			"Uncapturable"
		],
		"movement": 2
	},
	{
		"name": "Hive Extension Builder",
		"unitType": "Civilian",
		"replaces": "Great Engineer",
		"uniqueTo": "Insectoids",
		"uniques": 
		[
			"Can speed up construction of a building",
			"Can instantly construct a [Hive Extension] improvement <by consuming this unit>",
            		"Great Insectoid - [Production]", 
			"Unbuildable", 
			"Uncapturable"
		],
		"movement": 2
	},
	{
		"name": "Spirit Stones Builder",
		"replaces": "Great Prophet",
		"uniqueTo": "Insectoids",
		"unitType": "Civilian",
		"uniques": 
		[
            		"Can instantly construct a [Spirit Stones] improvement <by consuming this unit> <if it hasn't used other actions yet>",
            		"Can Spread Religion <for [2] movement> <[4] times> <after which this unit is consumed>",
			"Removes other religions when spreading religion",
            		"May found a religion <by consuming this unit> <if it hasn't used other actions yet>",
            		"May enhance a religion <by consuming this unit>  <if it hasn't used other actions yet>",
			"[-1] Sight", 
			"Great Insectoid - [Faith]",
			"Unbuildable", 
			"Religious Unit", 
			"Hidden when religion is disabled",
			"Takes your religion over the one in their birth city"
		],
		"movement": 2,
		"religiousStrength": 1000
	},
	{
		"name": "Hive Builder",
		"replaces": "Great General",
		"unitType": "Civilian",
		"uniques": 
		[
            		"Empire enters a [8]-turn Golden Age <by consuming this unit>",
            		"[+25]% Strength bonus for [Military] units within [2] tiles",
            		"Can instantly construct a [Defensive Base] improvement <by consuming this unit>",
			"Can be earned through combat",
			"Great Person - [War]", 
			"Unbuildable", 
			"Uncapturable"
		],
		"movement": 2
	},
	
]
